ollie/__init__.py
ollie/core/agent/planning_agent.py
ollie/core/agent/reader_agent.py
ollie/core/agent/writer_agent.py
ollie/core/config.py
ollie/core/prompt.py
ollie/main.py
ollie/provider/anthropic.py
ollie/provider/ollama.py
ollie/provider/openai.py
ollie/provider/provider.py
ollie/settings/ai_setup.py
ollie/settings/settings.py
ollie/ui/app.py
ollie/ui/bot.py
ollie/ui/callbacks.py
ollie/ui/chat_message.py
ollie/ui/markdown_parser.py
ollie/ui/styles.css
ollie-0.1.0.dist-info/WHEEL
ollie-0.1.0.dist-info/entry_points.txt
ollie-0.1.0.dist-info/METADATA
ollie-0.1.0.dist-info/RECORD
