Metadata-Version: 2.3
Name: ollie
Version: 0.1.0
Summary: Ollama-based code assistant
Requires-Dist: anthropic>=0.64.0
Requires-Dist: ollama>=0.5.3
Requires-Dist: openai>=1.99.9
Requires-Dist: python-dotenv>=1.1.1
Requires-Dist: requests>=2.32.4
Requires-Dist: rich>=14.1.0
Requires-Dist: textual-dev>=1.7.0
Requires-Dist: textual[syntax]>=5.3.0
Requires-Python: >=3.13
